{
    "results": [
        {
            "Xref": {
                "OrderId": 111,
                "OrderName": "ACtest"
            },
            "Order": {
                "OrderPrice": 10100,
                "Date": "2025-04-10T14:30:00.123",
                "Type": "Electronictest"
            }
        },
        {
            "Xref": {
                "OrderId": 112,
                "OrderName": "Laptoptest"
            },
            "Order": {
                "OrderPrice": 10100,
                "Date": "2025-04-10T14:30:00.123",
                "Type": "Electronictest"
            }
        }
    ]
}